jsonblueprint/__init__.py
jsonstruct/__init__.py
jsonblueprint-0.1.0.dist-info/METADATA
jsonblueprint-0.1.0.dist-info/WHEEL
jsonblueprint-0.1.0.dist-info/top_level.txt
jsonblueprint-0.1.0.dist-info/RECORD
