Metadata-Version: 2.1
Name: jsonblueprint
Version: 0.1.0
Summary: A package to extract and simplify JSON structure.
Home-page: https://github.com/gsusI/jsonblueprint
Author: Jesus Iniesta
Author-email: jesus.inica@gmail.com
Classifier: Development Status :: 3 - Alpha
Classifier: Intended Audience :: Developers
Classifier: License :: OSI Approved :: MIT License
Classifier: Programming Language :: Python :: 3.8
